{
  "timestamp": "2026-07-17T13:08:20Z",
  "run_id": "whisper-20260717T130820Z-domain-core-runtime-sync",
  "session_id": "session-20260717-whisper-maintenance",
  "sigil": "whisper",
  "tier": "spell",
  "mode": "generated_runtime_sync",
  "request": {
    "summary": "Install the improved DomainSpec Core Whisper runtime in the economy repository.",
    "intent": "Use the new convergence and delivery-flow behavior without losing the repository-local product research preset."
  },
  "execution": {
    "status": "completed",
    "outputs": [
      ".agents/skills/whisper/"
    ],
    "files_changed": [
      ".agents/skills/whisper/"
    ],
    "validation": [
      "yaml-package-parse:pass",
      "delivery-flow-pass-fixture:pass",
      "delivery-flow-fail-fixture:flag-intent-narration-and-duplicate-block",
      "local-product-research-preset-preserved:pass",
      "git-diff-check:pass"
    ],
    "notes": "The package was copied from the validated DomainSpec Core generated runtime. The repository-local product_research_blueprint overlay was preserved and was not promoted into public Arcanum.",
    "intent_state": "frozen",
    "correction_scope": "structure",
    "generated_output_count": 1,
    "derivative_fan_out_count": 1,
    "human_gate": "not_applicable",
    "transport_proof_status": "not_applicable"
  },
  "observer": {
    "quality_bar_status": "pass",
    "signals": [
      "quality-pass",
      "useful-pattern"
    ],
    "anti_pattern_hits": [],
    "workflow_gaps": [],
    "output_contract_drift": false,
    "reflection_trigger": "none",
    "recommendation": "observe the next five meaningful Whisper runs"
  },
  "target_artifact": ".agents/skills/whisper/SKILL.md",
  "dedupe_key": "whisper-20260717T130820Z-domain-core-runtime-sync:signal-observer:0.1.0",
  "observer_version": "0.1.0"
}
